MANIFEST.in
requirements.txt
setup.py
quarantine/__init__.py
quarantine/__main__.py
quarantine/cdc.py
quarantine.egg-info/PKG-INFO
quarantine.egg-info/SOURCES.txt
quarantine.egg-info/dependency_links.txt
quarantine.egg-info/entry_points.txt
quarantine.egg-info/requires.txt
quarantine.egg-info/top_level.txt