Metadata-Version: 1.0
Name: quarantine
Version: 0.1.0
Summary: A project that does things!
Home-page: https://github.com/Raynes/quarantine
Author: Anthony Grimes
Author-email: anemail@raynes.me
License: MIT
Platform: UNKNOWN
